ChineseDateTimeNLP/__init__.py
ChineseDateTimeNLP/enums.py
ChineseDateTimeNLP/normalizer.py
ChineseDateTimeNLP/point.py
ChineseDateTimeNLP/result.py
ChineseDateTimeNLP/unit.py
ChineseDateTimeNLP/helpers/LunarSolarConverter.py
ChineseDateTimeNLP/helpers/__init__.py
ChineseDateTimeNLP/helpers/arrow_helper.py
ChineseDateTimeNLP/helpers/int_common.py
ChineseDateTimeNLP/helpers/str_common.py
ChineseDateTimeNLP/resource/__init__.py
ChineseDateTimeNLP/resource/holiday.py
ChineseDateTimeNLP/resource/pattern.py
ChineseDateTimeNLP/tests/__init__.py
ChineseDateTimeNLP/tests/conftest.py
ChineseDateTimeNLP/tests/test_normalizer.py
ChineseDateTimeNLP/tests/test_point.py
ChineseDateTimeNLP/tests/test_utils.py
ChineseDateTimeNLP-3.0.2.dist-info/METADATA
ChineseDateTimeNLP-3.0.2.dist-info/WHEEL
ChineseDateTimeNLP-3.0.2.dist-info/top_level.txt
ChineseDateTimeNLP-3.0.2.dist-info/RECORD
