Metadata-Version: 2.1
Name: ChineseDateTimeNLP
Version: 3.0.2
Summary: 将中文时间表达词转为相应的时间字符串，支持时间点，时间段，时间间隔。
Home-page: https://github.com/xiaoyaosharenfan/ChineseDateTimeNLP
Author: Alex
Author-email: fanbinthu@163.com
License: MIT Licence
Keywords: nlp,time nlp,date nlp
Classifier: Programming Language :: Python :: 3.7
Requires-Dist: arrow (>=0.17.0)
Requires-Dist: loguru (>=0.5.3)
Requires-Dist: regex (>=2020.11.13)
